tchu_tchu/__init__.py
tchu_tchu/client.py
tchu_tchu/django/__init__.py
tchu_tchu/django/celery.py
tchu_tchu/django/decorators.py
tchu_tchu/django/mixins.py
tchu_tchu/django/signals.py
tchu_tchu/events.py
tchu_tchu/logging/__init__.py
tchu_tchu/logging/formatters.py
tchu_tchu/logging/handlers.py
tchu_tchu/metrics/__init__.py
tchu_tchu/metrics/collectors.py
tchu_tchu/metrics/exporters.py
tchu_tchu/producer.py
tchu_tchu/registry.py
tchu_tchu/serializers/__init__.py
tchu_tchu/serverless_producer.py
tchu_tchu/subscriber.py
tchu_tchu/utils/__init__.py
tchu_tchu/utils/error_handling.py
tchu_tchu/utils/json_encoder.py
tchu_tchu/utils/response_handler.py
tchu_tchu/version.py
tchu_tchu-3.0.3.dist-info/METADATA
tchu_tchu-3.0.3.dist-info/WHEEL
tchu_tchu-3.0.3.dist-info/licenses/LICENSE
tchu_tchu-3.0.3.dist-info/RECORD
