Metadata-Version: 2.4
Name: tchu-tchu
Version: 3.0.3
Summary: A modern Celery-based messaging library with true broadcast support for microservices
License: MIT
License-File: LICENSE
Keywords: celery,messaging,pydantic,django,events,pubsub,broadcast,microservices
Author: David Sigley
Author-email: djsigley@gmail.com
Requires-Python: >=3.8,<4.0
Classifier: Development Status :: 4 - Beta
Classifier: Framework :: Celery
Classifier: Framework :: Django
Classifier: Intended Audience :: Developers
Classifier: License :: OSI Approved :: MIT License
Classifier: Programming Language :: Python :: 3
Classifier: Programming Language :: Python :: 3.8
Classifier: Programming Language :: Python :: 3.9
Classifier: Programming Language :: Python :: 3.10
Classifier: Programming Language :: Python :: 3.11
Classifier: Programming Language :: Python :: 3.12
Classifier: Programming Language :: Python :: 3.13
Classifier: Programming Language :: Python :: 3.14
Provides-Extra: all
Provides-Extra: django
Provides-Extra: protobuf
Requires-Dist: celery (>=5.3.0,<6.0.0)
Requires-Dist: django (>=4.0.0,<5.0.0) ; extra == "django" or extra == "all"
Requires-Dist: kombu (>=5.3.0,<6.0.0)
Requires-Dist: protobuf (>=4.0.0,<5.0.0) ; extra == "protobuf" or extra == "all"
Requires-Dist: pydantic (>=2.0.0,<3.0.0)
Project-URL: Documentation, https://github.com/sigularusrex/tchu-tchu
Project-URL: Homepage, https://github.com/sigularusrex/tchu-tchu
Project-URL: Repository, https://github.com/sigularusrex/tchu-tchu
